Load_Prediction/__init__.py
Load_Prediction/common_function.py
Load_Prediction/load_prediction.py
Load_Prediction/main_load.py
Load_Prediction/mssql_auth.py
Load_Prediction-0.0.1.3.dist-info/METADATA
Load_Prediction-0.0.1.3.dist-info/WHEEL
Load_Prediction-0.0.1.3.dist-info/top_level.txt
Load_Prediction-0.0.1.3.dist-info/RECORD
