Metadata-Version: 2.1
Name: Load-Prediction
Version: 0.0.1.3
Summary: Sunghan Load Prediction
Home-page: https://github.com/tathata21/moon
Author: SungHan
Author-email: shbems777@gmail.com
License: SH
Platform: UNKNOWN
Requires-Python: >=3
Requires-Dist: pymssql
